MANIFEST.in
NEWS.rst
README.rst
setup.py
ast/ast_cython.py
ast/ast_cython.pyc
ast/ast_cython_c.py
ast/ast_cython_c.pyc
ast/ast_cython_impl.py
ast/ast_cython_impl.pyc
ast/ast_cython_visitor.py
ast/ast_cython_visitor.pyc
ast/ast_cython_visitor_impl.py
ast/ast_cython_visitor_impl.pyc
ast/build_ast.py
examples/visitor_example.py
graphql_parser/GraphQLAst.pxd
graphql_parser/GraphQLAst.pyx
graphql_parser/GraphQLAstNode.pxd
graphql_parser/GraphQLAstNode.pyx
graphql_parser/GraphQLAstVisitor.pyx
graphql_parser/GraphQLParser.pyx
graphql_parser/__init__.py
graphql_parser/cGraphQLAst.pxd
graphql_parser/cGraphQLAstNode.pxd
graphql_parser/cGraphQLAstVisitor.pxd
graphql_parser/cGraphQLParser.pxd
graphqlparser.egg-info/PKG-INFO
graphqlparser.egg-info/SOURCES.txt
graphqlparser.egg-info/dependency_links.txt
graphqlparser.egg-info/requires.txt
graphqlparser.egg-info/top_level.txt