Metadata-Version: 1.1
Name: graphqlparser
Version: 0.0.3
Summary: Python bindings for libgraphqlparser (Cython-based)
Home-page: https://github.com/elastic-coders/py-graphqlparser
Author: Marco Paolini
Author-email: markopaolini@gmail.com
License: UNKNOWN
Platform: UNKNOWN
Classifier: Development Status :: 3 - Alpha
Classifier: Environment :: Console
Classifier: Environment :: Web Environment
Classifier: Intended Audience :: Developers
Classifier: License :: OSI Approved :: BSD License
Classifier: Operating System :: POSIX :: Linux
Classifier: Programming Language :: Python :: Implementation :: CPython
Classifier: Topic :: Internet :: WWW/HTTP
Classifier: Topic :: Software Development :: Libraries :: Python Modules
